aif360/README.md
aif360/__init__.py
aif360/decorating_metaclass.py
aif360/version.py
aif360/algorithms/__init__.py
aif360/algorithms/transformer.py
aif360/algorithms/inprocessing/__init__.py
aif360/algorithms/inprocessing/adversarial_debiasing.py
aif360/algorithms/inprocessing/art_classifier.py
aif360/algorithms/inprocessing/exponentiated_gradient_reduction.py
aif360/algorithms/inprocessing/gerryfair_classifier.py
aif360/algorithms/inprocessing/grid_search_reduction.py
aif360/algorithms/inprocessing/meta_fair_classifier.py
aif360/algorithms/inprocessing/prejudice_remover.py
aif360/algorithms/inprocessing/celisMeta/FalseDiscovery.py
aif360/algorithms/inprocessing/celisMeta/General.py
aif360/algorithms/inprocessing/celisMeta/StatisticalRate.py
aif360/algorithms/inprocessing/celisMeta/__init__.py
aif360/algorithms/inprocessing/gerryfair/__init__.py
aif360/algorithms/inprocessing/gerryfair/auditor.py
aif360/algorithms/inprocessing/gerryfair/classifier_history.py
aif360/algorithms/inprocessing/gerryfair/clean.py
aif360/algorithms/inprocessing/gerryfair/fairness_plots.py
aif360/algorithms/inprocessing/gerryfair/heatmap.py
aif360/algorithms/inprocessing/gerryfair/learner.py
aif360/algorithms/inprocessing/gerryfair/reg_oracle_class.py
aif360/algorithms/inprocessing/kamfadm-2012ecmlpkdd/__init__.py
aif360/algorithms/inprocessing/kamfadm-2012ecmlpkdd/predict_lr.py
aif360/algorithms/inprocessing/kamfadm-2012ecmlpkdd/train_pr.py
aif360/algorithms/inprocessing/kamfadm-2012ecmlpkdd/fadm/__init__.py
aif360/algorithms/inprocessing/kamfadm-2012ecmlpkdd/fadm/lr/__init__.py
aif360/algorithms/inprocessing/kamfadm-2012ecmlpkdd/fadm/lr/pr.py
aif360/algorithms/inprocessing/kamfadm-2012ecmlpkdd/fadm/util/__init__.py
aif360/algorithms/inprocessing/kamfadm-2012ecmlpkdd/fadm/util/_base.py
aif360/algorithms/postprocessing/__init__.py
aif360/algorithms/postprocessing/calibrated_eq_odds_postprocessing.py
aif360/algorithms/postprocessing/deterministic_reranking.py
aif360-0.6.1.dist-info/LICENSE
aif360-0.6.1.dist-info/METADATA
aif360-0.6.1.dist-info/WHEEL
aif360-0.6.1.dist-info/top_level.txt
aif360-0.6.1.dist-info/RECORD
